liteq/__init__.py
liteq/cli.py
liteq/core.py
liteq/db.py
liteq/monitoring.py
liteq/web.py
liteq/worker.py
liteq/templates/dashboard.html
liteq-0.2.0.dist-info/licenses/LICENSE
liteq-0.2.0.dist-info/METADATA
liteq-0.2.0.dist-info/WHEEL
liteq-0.2.0.dist-info/entry_points.txt
liteq-0.2.0.dist-info/top_level.txt
liteq-0.2.0.dist-info/RECORD
