Metadata-Version: 2.4
Name: liteq
Version: 0.2.0
Summary: A lightweight message queue for Python with no dependencies
Author-email: Arkadiy Senin <senin.arkadiy@gmail.com>
License: MIT
Project-URL: Homepage, https://github.com/ddreamboy/liteq
Project-URL: Documentation, https://github.com/ddreamboy/liteq#readme
Project-URL: Repository, https://github.com/ddreamboy/liteq.git
Project-URL: Issues, https://github.com/ddreamboy/liteq/issues
Keywords: queue,task,async,message-queue,job-queue,background-tasks
Classifier: Development Status :: 4 - Beta
Classifier: Intended Audience :: Developers
Classifier: License :: OSI Approved :: MIT License
Classifier: Programming Language :: Python :: 3
Classifier: Programming Language :: Python :: 3.10
Classifier: Programming Language :: Python :: 3.11
Classifier: Programming Language :: Python :: 3.12
Classifier: Topic :: Software Development :: Libraries :: Python Modules
Classifier: Topic :: System :: Distributed Computing
Requires-Python: >=3.10
License-File: LICENSE
Provides-Extra: test
Requires-Dist: pytest>=7.0; extra == "test"
Requires-Dist: pytest-cov>=4.0; extra == "test"
Provides-Extra: dev
Requires-Dist: pytest>=7.0; extra == "dev"
Requires-Dist: pytest-cov>=4.0; extra == "dev"
Requires-Dist: black>=22.0; extra == "dev"
Requires-Dist: ruff>=0.1; extra == "dev"
Requires-Dist: build>=1.0; extra == "dev"
Requires-Dist: twine>=4.0; extra == "dev"
Provides-Extra: web
Requires-Dist: fastapi>=0.104.0; extra == "web"
Requires-Dist: uvicorn[standard]>=0.24.0; extra == "web"
Requires-Dist: jinja2>=3.1.0; extra == "web"
Dynamic: license-file
Dynamic: requires-python
